diamentowa_bukmacherska/__init__.py
diamentowa_bukmacherska/diamentowa_bukmacherska.py
diamentowa_bukmacherska-0.1.1.dist-info/LICENSE
diamentowa_bukmacherska-0.1.1.dist-info/METADATA
diamentowa_bukmacherska-0.1.1.dist-info/WHEEL
diamentowa_bukmacherska-0.1.1.dist-info/top_level.txt
diamentowa_bukmacherska-0.1.1.dist-info/RECORD
