Metadata-Version: 2.2
Name: diamentowa_bukmacherska
Version: 0.1.1
Summary: Zaawansowana biblioteka do analiz bukmacherskich
Home-page: https://github.com/twoje-repozytorium/diamentowa_bukmacherska
Author: Twoje Imię
Author-email: twoj.email@example.com
License: MIT
Classifier: Programming Language :: Python :: 3
Classifier: License :: OSI Approved :: MIT License
Classifier: Operating System :: OS Independent
Requires-Python: >=3.7
License-File: LICENSE
Dynamic: author
Dynamic: author-email
Dynamic: classifier
Dynamic: description
Dynamic: description-content-type
Dynamic: home-page
Dynamic: license
Dynamic: requires-python
Dynamic: summary
